gribjumplib/__init__.py
gribjumplib/bin/gribjump-dump-info
gribjumplib/bin/gribjump-extract
gribjumplib/bin/gribjump-info
gribjumplib/bin/gribjump-scan
gribjumplib/bin/gribjump-scan-files
gribjumplib/bin/gribjump-server
gribjumplib/bin/gribjump-validate
gribjumplib/include/gribjump/Config.h
gribjumplib/include/gribjump/Engine.h
gribjumplib/include/gribjump/ExtractionData.h
gribjumplib/include/gribjump/ExtractionItem.h
gribjumplib/include/gribjump/FDBPlugin.h
gribjumplib/include/gribjump/Forwarder.h
gribjumplib/include/gribjump/GribJump.h
gribjumplib/include/gribjump/GribJumpBase.h
gribjumplib/include/gribjump/GribJumpDataAccessor.h
gribjumplib/include/gribjump/GribJumpException.h
gribjumplib/include/gribjump/GribJumpFactory.h
gribjumplib/include/gribjump/LibGribJump.h
gribjumplib/include/gribjump/Lister.h
gribjumplib/include/gribjump/LocalGribJump.h
gribjumplib/include/gribjump/LogRouter.h
gribjumplib/include/gribjump/Metrics.h
gribjumplib/include/gribjump/Stats.h
gribjumplib/include/gribjump/Task.h
gribjumplib/include/gribjump/URIHelper.h
gribjumplib/include/gribjump/gribjump_c.h
gribjumplib/include/gribjump/gribjump_config.h
gribjumplib/include/gribjump/gribjump_ecbuild_config.h
gribjumplib/include/gribjump/gribjump_version.h
gribjumplib/include/gribjump/api/ExtractionIterator.h
gribjumplib/include/gribjump/compression/DataAccessor.h
gribjumplib/include/gribjump/compression/NumericCompressor.h
gribjumplib/include/gribjump/compression/Range.h
gribjumplib/include/gribjump/compression/compressors/Aec.h
gribjumplib/include/gribjump/compression/compressors/Ccsds.h
gribjumplib/include/gribjump/compression/compressors/Simple.h
gribjumplib/include/gribjump/compression/compressors/SimplePacking.h
gribjumplib/include/gribjump/info/CcsdsInfo.h
gribjumplib/include/gribjump/info/InfoAggregator.h
gribjumplib/include/gribjump/info/InfoCache.h
gribjumplib/include/gribjump/info/InfoExtractor.h
gribjumplib/include/gribjump/info/InfoFactory.h
gribjumplib-0.10.3.9.dist-info/licenses/LICENSE
gribjumplib-0.10.3.9.dist-info/METADATA
gribjumplib-0.10.3.9.dist-info/WHEEL
gribjumplib-0.10.3.9.dist-info/top_level.txt
gribjumplib-0.10.3.9.dist-info/RECORD
