Metadata-Version: 2.4
Name: gribjumplib
Version: 0.10.3.9
Summary: "gribjumplib"
Author: file: AUTHORS
License-File: LICENSE
Requires-Dist: eckitlib==1.32.4.9
Requires-Dist: eccodeslib==2.45.1.9
Requires-Dist: metkitlib==1.16.0.9
Requires-Dist: fdb5lib==5.19.0.9
Dynamic: license-file
Dynamic: requires-dist
